[
  {
    "ContainingType": "Server.Controllers.authController",
    "Method": "Login",
    "RelativePath": "api/auth/Login",
    "HttpMethod": "POST",
    "IsController": true,
    "Order": 0,
    "Parameters": [
      {
        "Name": "login",
        "Type": "Server.Models.DTOs.LoginDTO",
        "IsRequired": true
      }
    ],
    "ReturnTypes": []
  },
  {
    "ContainingType": "Server.Controllers.authController",
    "Method": "Register",
    "RelativePath": "api/auth/Register",
    "HttpMethod": "POST",
    "IsController": true,
    "Order": 0,
    "Parameters": [
      {
        "Name": "register",
        "Type": "Server.Models.DTOs.RegisterDTO",
        "IsRequired": true
      }
    ],
    "ReturnTypes": []
  },
  {
    "ContainingType": "Server.Controllers.DataController",
    "Method": "addCriteria",
    "RelativePath": "api/Data/AddCriteria",
    "HttpMethod": "POST",
    "IsController": true,
    "Order": 0,
    "Parameters": [
      {
        "Name": "criteria",
        "Type": "Server.Models.DTOs.CriteriaDTO",
        "IsRequired": true
      }
    ],
    "ReturnTypes": []
  },
  {
    "ContainingType": "Server.Controllers.DataController",
    "Method": "addStatus",
    "RelativePath": "api/Data/AddStatus",
    "HttpMethod": "POST",
    "IsController": true,
    "Order": 0,
    "Parameters": [
      {
        "Name": "status",
        "Type": "Server.Models.DTOs.StatusDTO",
        "IsRequired": true
      }
    ],
    "ReturnTypes": []
  },
  {
    "ContainingType": "Server.Controllers.DataController",
    "Method": "getDashboardData",
    "RelativePath": "api/Data/dashboardData",
    "HttpMethod": "GET",
    "IsController": true,
    "Order": 0,
    "Parameters": [],
    "ReturnTypes": []
  },
  {
    "ContainingType": "Server.Controllers.DataController",
    "Method": "getAllCriteria",
    "RelativePath": "api/Data/getAllCriteria",
    "HttpMethod": "GET",
    "IsController": true,
    "Order": 0,
    "Parameters": [],
    "ReturnTypes": []
  },
  {
    "ContainingType": "Server.Controllers.DataController",
    "Method": "getAllDept",
    "RelativePath": "api/Data/getAllDept",
    "HttpMethod": "GET",
    "IsController": true,
    "Order": 0,
    "Parameters": [],
    "ReturnTypes": []
  },
  {
    "ContainingType": "Server.Controllers.DataController",
    "Method": "getAllManager",
    "RelativePath": "api/Data/getAllManager",
    "HttpMethod": "GET",
    "IsController": true,
    "Order": 0,
    "Parameters": [],
    "ReturnTypes": []
  },
  {
    "ContainingType": "Server.Controllers.DataController",
    "Method": "getAllRole",
    "RelativePath": "api/Data/getAllRole",
    "HttpMethod": "GET",
    "IsController": true,
    "Order": 0,
    "Parameters": [],
    "ReturnTypes": []
  },
  {
    "ContainingType": "Server.Controllers.EmployeeController",
    "Method": "deleteEmployee",
    "RelativePath": "api/Employee/deleteEmp/{id}",
    "HttpMethod": "DELETE",
    "IsController": true,
    "Order": 0,
    "Parameters": [
      {
        "Name": "id",
        "Type": "System.Int32",
        "IsRequired": true
      }
    ],
    "ReturnTypes": []
  },
  {
    "ContainingType": "Server.Controllers.EmployeeController",
    "Method": "editEmp",
    "RelativePath": "api/Employee/editEmp/{id}",
    "HttpMethod": "PUT",
    "IsController": true,
    "Order": 0,
    "Parameters": [
      {
        "Name": "id",
        "Type": "System.Int32",
        "IsRequired": true
      },
      {
        "Name": "registerDTO",
        "Type": "Server.Models.DTOs.RegisterDTO",
        "IsRequired": true
      }
    ],
    "ReturnTypes": []
  },
  {
    "ContainingType": "Server.Controllers.EmployeeController",
    "Method": "getEmp",
    "RelativePath": "api/Employee/getEmp/{id}",
    "HttpMethod": "GET",
    "IsController": true,
    "Order": 0,
    "Parameters": [
      {
        "Name": "id",
        "Type": "System.Int32",
        "IsRequired": true
      }
    ],
    "ReturnTypes": []
  },
  {
    "ContainingType": "Server.Controllers.EmployeeController",
    "Method": "GetAllEmployees",
    "RelativePath": "api/Employee/getEmployee/{pageNumber}",
    "HttpMethod": "GET",
    "IsController": true,
    "Order": 0,
    "Parameters": [
      {
        "Name": "pageNumber",
        "Type": "System.Int32",
        "IsRequired": true
      },
      {
        "Name": "pageSize",
        "Type": "System.Int32",
        "IsRequired": false
      },
      {
        "Name": "search",
        "Type": "System.String",
        "IsRequired": false
      },
      {
        "Name": "deptId",
        "Type": "System.Nullable\u00601[[System.Int32, System.Private.CoreLib, Version=8.0.0.0, Culture=neutral, PublicKeyToken=7cec85d7bea7798e]]",
        "IsRequired": false
      },
      {
        "Name": "orderBy",
        "Type": "System.String",
        "IsRequired": false
      }
    ],
    "ReturnTypes": []
  },
  {
    "ContainingType": "Server.Controllers.GoalController",
    "Method": "addGoal",
    "RelativePath": "api/Goal/AddGoal",
    "HttpMethod": "POST",
    "IsController": true,
    "Order": 0,
    "Parameters": [
      {
        "Name": "goal",
        "Type": "Server.Models.DTOs.GoalDTO",
        "IsRequired": true
      }
    ],
    "ReturnTypes": []
  },
  {
    "ContainingType": "Server.Controllers.GoalController",
    "Method": "deleteGoal",
    "RelativePath": "api/Goal/DeleteGoal/{goalId}",
    "HttpMethod": "DELETE",
    "IsController": true,
    "Order": 0,
    "Parameters": [
      {
        "Name": "goalId",
        "Type": "System.Int32",
        "IsRequired": true
      }
    ],
    "ReturnTypes": []
  },
  {
    "ContainingType": "Server.Controllers.GoalController",
    "Method": "editGoal",
    "RelativePath": "api/Goal/EditGoal/{goalId}",
    "HttpMethod": "PUT",
    "IsController": true,
    "Order": 0,
    "Parameters": [
      {
        "Name": "goalId",
        "Type": "System.Int32",
        "IsRequired": true
      },
      {
        "Name": "goal",
        "Type": "Server.Models.DTOs.GoalDTO",
        "IsRequired": true
      }
    ],
    "ReturnTypes": []
  },
  {
    "ContainingType": "Server.Controllers.GoalController",
    "Method": "getAllGoals",
    "RelativePath": "api/Goal/GetAllGoals/{pageNumber}",
    "HttpMethod": "GET",
    "IsController": true,
    "Order": 0,
    "Parameters": [
      {
        "Name": "pageNumber",
        "Type": "System.Int32",
        "IsRequired": true
      },
      {
        "Name": "pageSize",
        "Type": "System.Int32",
        "IsRequired": false
      },
      {
        "Name": "search",
        "Type": "System.String",
        "IsRequired": false
      },
      {
        "Name": "statusId",
        "Type": "System.Nullable\u00601[[System.Int32, System.Private.CoreLib, Version=8.0.0.0, Culture=neutral, PublicKeyToken=7cec85d7bea7798e]]",
        "IsRequired": false
      }
    ],
    "ReturnTypes": []
  },
  {
    "ContainingType": "Server.Controllers.GoalController",
    "Method": "getGoal",
    "RelativePath": "api/Goal/GetGoal/{goalId}",
    "HttpMethod": "GET",
    "IsController": true,
    "Order": 0,
    "Parameters": [
      {
        "Name": "goalId",
        "Type": "System.Int32",
        "IsRequired": true
      }
    ],
    "ReturnTypes": []
  },
  {
    "ContainingType": "Server.Controllers.notificationController",
    "Method": "ClearAll",
    "RelativePath": "api/notification/ClearAll",
    "HttpMethod": "PUT",
    "IsController": true,
    "Order": 0,
    "Parameters": [],
    "ReturnTypes": []
  },
  {
    "ContainingType": "Server.Controllers.notificationController",
    "Method": "GetAllNotifications",
    "RelativePath": "api/notification/GetAllNotification",
    "HttpMethod": "GET",
    "IsController": true,
    "Order": 0,
    "Parameters": [],
    "ReturnTypes": []
  },
  {
    "ContainingType": "Server.Controllers.notificationController",
    "Method": "MarkAsRead",
    "RelativePath": "api/notification/MarkAsRead/{Id}",
    "HttpMethod": "PUT",
    "IsController": true,
    "Order": 0,
    "Parameters": [
      {
        "Name": "Id",
        "Type": "System.Int32",
        "IsRequired": true
      }
    ],
    "ReturnTypes": []
  },
  {
    "ContainingType": "Server.Controllers.ReportController",
    "Method": "GenerateReport",
    "RelativePath": "api/Report/GenerateReport/{reviewId}",
    "HttpMethod": "GET",
    "IsController": true,
    "Order": 0,
    "Parameters": [
      {
        "Name": "reviewId",
        "Type": "System.Int32",
        "IsRequired": true
      }
    ],
    "ReturnTypes": []
  },
  {
    "ContainingType": "Server.Controllers.ReportController",
    "Method": "GetAllReport",
    "RelativePath": "api/Report/GetAllReport/{pageNumber}",
    "HttpMethod": "GET",
    "IsController": true,
    "Order": 0,
    "Parameters": [
      {
        "Name": "pageNumber",
        "Type": "System.Int32",
        "IsRequired": true
      },
      {
        "Name": "pageSize",
        "Type": "System.Int32",
        "IsRequired": false
      },
      {
        "Name": "startDate",
        "Type": "System.Nullable\u00601[[System.DateOnly, System.Private.CoreLib, Version=8.0.0.0, Culture=neutral, PublicKeyToken=7cec85d7bea7798e]]",
        "IsRequired": false
      },
      {
        "Name": "endDate",
        "Type": "System.Nullable\u00601[[System.DateOnly, System.Private.CoreLib, Version=8.0.0.0, Culture=neutral, PublicKeyToken=7cec85d7bea7798e]]",
        "IsRequired": false
      },
      {
        "Name": "deptId",
        "Type": "System.Nullable\u00601[[System.Int32, System.Private.CoreLib, Version=8.0.0.0, Culture=neutral, PublicKeyToken=7cec85d7bea7798e]]",
        "IsRequired": false
      }
    ],
    "ReturnTypes": []
  },
  {
    "ContainingType": "Server.Controllers.ReviewController",
    "Method": "deleteSelfReview",
    "RelativePath": "api/Review/deleteSelfReview/{id}",
    "HttpMethod": "DELETE",
    "IsController": true,
    "Order": 0,
    "Parameters": [
      {
        "Name": "id",
        "Type": "System.Int32",
        "IsRequired": true
      }
    ],
    "ReturnTypes": []
  },
  {
    "ContainingType": "Server.Controllers.ReviewController",
    "Method": "EditSelfReview",
    "RelativePath": "api/Review/EditSelfReview/{id}",
    "HttpMethod": "PUT",
    "IsController": true,
    "Order": 0,
    "Parameters": [
      {
        "Name": "id",
        "Type": "System.Int32",
        "IsRequired": true
      },
      {
        "Name": "selfreview",
        "Type": "Server.Models.DTOs.selfReviewDTO",
        "IsRequired": true
      }
    ],
    "ReturnTypes": []
  },
  {
    "ContainingType": "Server.Controllers.ReviewController",
    "Method": "getReview",
    "RelativePath": "api/Review/getReview",
    "HttpMethod": "GET",
    "IsController": true,
    "Order": 0,
    "Parameters": [
      {
        "Name": "id",
        "Type": "System.Int32",
        "IsRequired": false
      }
    ],
    "ReturnTypes": []
  },
  {
    "ContainingType": "Server.Controllers.ReviewController",
    "Method": "managerReview",
    "RelativePath": "api/Review/ManagerReview",
    "HttpMethod": "PUT",
    "IsController": true,
    "Order": 0,
    "Parameters": [
      {
        "Name": "managerReview",
        "Type": "Server.Models.DTOs.managerReviewDTO",
        "IsRequired": true
      }
    ],
    "ReturnTypes": []
  },
  {
    "ContainingType": "Server.Controllers.ReviewController",
    "Method": "managerReviewList",
    "RelativePath": "api/Review/managerReviewList/{pageNumber}",
    "HttpMethod": "GET",
    "IsController": true,
    "Order": 0,
    "Parameters": [
      {
        "Name": "pageNumber",
        "Type": "System.Int32",
        "IsRequired": true
      },
      {
        "Name": "search",
        "Type": "System.String",
        "IsRequired": false
      },
      {
        "Name": "rating",
        "Type": "System.Nullable\u00601[[System.Int32, System.Private.CoreLib, Version=8.0.0.0, Culture=neutral, PublicKeyToken=7cec85d7bea7798e]]",
        "IsRequired": false
      }
    ],
    "ReturnTypes": []
  },
  {
    "ContainingType": "Server.Controllers.ReviewController",
    "Method": "managerRevise",
    "RelativePath": "api/Review/ManagerRevise/{id}",
    "HttpMethod": "PUT",
    "IsController": true,
    "Order": 0,
    "Parameters": [
      {
        "Name": "id",
        "Type": "System.Int32",
        "IsRequired": true
      },
      {
        "Name": "managerFeedback",
        "Type": "System.String",
        "IsRequired": false
      }
    ],
    "ReturnTypes": []
  },
  {
    "ContainingType": "Server.Controllers.ReviewController",
    "Method": "selfReview",
    "RelativePath": "api/Review/SelfReview",
    "HttpMethod": "POST",
    "IsController": true,
    "Order": 0,
    "Parameters": [
      {
        "Name": "selfReviewDTO",
        "Type": "Server.Models.DTOs.selfReviewDTO",
        "IsRequired": true
      }
    ],
    "ReturnTypes": []
  },
  {
    "ContainingType": "Server.Controllers.ReviewController",
    "Method": "selfReviewList",
    "RelativePath": "api/Review/SelfReviewList/{pageNumber}",
    "HttpMethod": "GET",
    "IsController": true,
    "Order": 0,
    "Parameters": [
      {
        "Name": "pageNumber",
        "Type": "System.Int32",
        "IsRequired": true
      },
      {
        "Name": "pageSize",
        "Type": "System.Int32",
        "IsRequired": false
      },
      {
        "Name": "search",
        "Type": "System.String",
        "IsRequired": false
      },
      {
        "Name": "statusId",
        "Type": "System.Nullable\u00601[[System.Int32, System.Private.CoreLib, Version=8.0.0.0, Culture=neutral, PublicKeyToken=7cec85d7bea7798e]]",
        "IsRequired": false
      }
    ],
    "ReturnTypes": []
  }
]